demand_pred_model/__init__.py
demand_pred_model/_modidx.py
demand_pred_model/model.py
demand_pred_model-0.0.2.dist-info/LICENSE
demand_pred_model-0.0.2.dist-info/METADATA
demand_pred_model-0.0.2.dist-info/WHEEL
demand_pred_model-0.0.2.dist-info/entry_points.txt
demand_pred_model-0.0.2.dist-info/top_level.txt
demand_pred_model-0.0.2.dist-info/RECORD
