Metadata-Version: 2.1
Name: demand-pred-model
Version: 0.0.2
Summary: An ML model to predict demand in E-commerce
Home-page: https://github.com/f.ghavamian/demand_pred_model
Author: Fariborz Ghavamian
Author-email: fari.ghavamian@gmail.com
License: Apache Software License 2.0
Keywords: nbdev jupyter notebook python
Platform: UNKNOWN
Classifier: Development Status :: 4 - Beta
Classifier: Intended Audience :: Developers
Classifier: Natural Language :: English
Classifier: Programming Language :: Python :: 3.7
Classifier: Programming Language :: Python :: 3.8
Classifier: Programming Language :: Python :: 3.9
Classifier: Programming Language :: Python :: 3.10
Classifier: License :: OSI Approved :: Apache Software License
Requires-Python: >=3.7
Requires-Dist: numpy
Requires-Dist: pandas
Requires-Dist: prophet
Requires-Dist: sktime
Provides-Extra: dev
Requires-Dist: matplotlib ; extra == 'dev'
Requires-Dist: seaborn ; extra == 'dev'
